ytdl_taquitos/__init__.py
ytdl_taquitos/downloader.py
ytdl_taquitos/extractor/base_extractor.py
ytdl_taquitos/extractor/youtube.py
ytdl_taquitos-0.1.1.dist-info/METADATA
ytdl_taquitos-0.1.1.dist-info/WHEEL
ytdl_taquitos-0.1.1.dist-info/top_level.txt
ytdl_taquitos-0.1.1.dist-info/RECORD
