Metadata-Version: 2.4
Name: ytdl-taquitos
Version: 0.1.1
Summary: A modern YouTube and video platform downloader library
Home-page: https://github.com/JuandeMx/ytdl-taquitos
Author: JuandeMx
Author-email: jgjuande.mx@gmail.com
Project-URL: Bug Reports, https://github.com/JuandeMx/ytdl-taquitos/issues
Project-URL: Source, https://github.com/JuandeMx/ytdl-taquitos
Project-URL: Documentation, https://github.com/JuandeMx/ytdl-taquitos#readme
Keywords: youtube downloader video audio async
Classifier: Development Status :: 3 - Alpha
Classifier: Intended Audience :: Developers
Classifier: License :: OSI Approved :: MIT License
Classifier: Operating System :: OS Independent
Classifier: Programming Language :: Python :: 3
Classifier: Programming Language :: Python :: 3.8
Classifier: Programming Language :: Python :: 3.9
Classifier: Programming Language :: Python :: 3.10
Classifier: Programming Language :: Python :: 3.11
Classifier: Topic :: Internet :: WWW/HTTP :: Dynamic Content
Classifier: Topic :: Multimedia :: Video
Classifier: Topic :: Software Development :: Libraries :: Python Modules
Requires-Python: >=3.8
Requires-Dist: aiohttp>=3.8.0
Requires-Dist: tqdm>=4.65.0
Requires-Dist: ffmpeg-python>=0.2.0
Requires-Dist: beautifulsoup4>=4.12.0
Requires-Dist: mutagen>=1.46.0
Requires-Dist: yt-dlp>=2024.3.10
Provides-Extra: dev
Requires-Dist: pytest>=7.0.0; extra == "dev"
Requires-Dist: pytest-asyncio>=0.21.0; extra == "dev"
Requires-Dist: black>=22.3.0; extra == "dev"
Requires-Dist: isort>=5.10.1; extra == "dev"
Requires-Dist: flake8>=4.0.1; extra == "dev"
Dynamic: author
Dynamic: author-email
Dynamic: classifier
Dynamic: description
Dynamic: description-content-type
Dynamic: home-page
Dynamic: keywords
Dynamic: project-url
Dynamic: provides-extra
Dynamic: requires-dist
Dynamic: requires-python
Dynamic: summary
